{
  "kind": "collectionType",
  "collectionName": "user_goal_milestones",
  "info": {
    "singularName": "user-goal-milestone",
    "pluralName": "user-goal-milestones",
    "displayName": "User Goal Milestone"
  },
  "options": {
    "draftAndPublish": false
  },
  "pluginOptions": {},
  "attributes": {
    "user_goal": {
      "type": "relation",
      "relation": "oneToOne",
      "target": "api::user-goal.user-goal"
    },
    "title": {
      "type": "string"
    },
    "note": {
      "type": "string"
    },
    "target_date": {
      "type": "datetime"
    },
    "completed_at": {
      "type": "datetime"
    },
    "sort_order": {
      "type": "integer"
    }
  }
}
